setup.py
listy/__init__.py
listy/counter.py
listy/deterministic_cached_model.py
listy/list_cache.py
listy/middleware.py
listy/on_demand_pickle.py
listy/utils.py
listy_django_cache.egg-info/PKG-INFO
listy_django_cache.egg-info/SOURCES.txt
listy_django_cache.egg-info/dependency_links.txt
listy_django_cache.egg-info/requires.txt
listy_django_cache.egg-info/top_level.txt