Metadata-Version: 1.0
Name: listy-django-cache
Version: 0.9.0
Summary: A deterministic caching mechanism for Django
Home-page: https://github.com/wavii/listy-django-cache
Author: Wavii, Inc.
Author-email: info@wavii.com
License: MIT License
Platform: UNKNOWN
